sspa/__init__.py
sspa/download_pathways.py
sspa/identifier_conversion.py
sspa/process_pathways.py
sspa/process_pathways_dictionary.py
sspa/sspa_cluster.py
sspa/sspa_fgsea.py
sspa/sspa_gsea.py
sspa/sspa_gsva.py
sspa/sspa_kpca.py
sspa/sspa_ora.py
sspa/sspa_ssGSEA.py
sspa/sspa_svd.py
sspa/sspa_zscore.py
sspa/utils.py
sspa/example_data/BXD_mouse_metabolomics.csv
sspa/example_data/BXD_mouse_metabolomics_raw_data.csv
sspa/example_data/Su_covid_metabolomics_processed.csv
sspa/example_data/Su_metab_data_raw.csv
sspa/pathway_databases/ChEBI2Reactome_All_Levels_R78.txt
sspa/pathway_databases/KEGG_human_pathways_compounds_R98.csv
sspa/pathway_databases/wikipathways-20220610-gmt-Homo_sapiens.gmt
sspa-1.0.4.dist-info/LICENSE
sspa-1.0.4.dist-info/METADATA
sspa-1.0.4.dist-info/WHEEL
sspa-1.0.4.dist-info/top_level.txt
sspa-1.0.4.dist-info/RECORD
