Metadata-Version: 2.1
Name: sspa
Version: 1.0.4
Summary: Single sample pathway analysis tools for omics data
Home-page: https://github.com/cwieder/sspa
Author: Cecilia Wieder
Author-email: cw2019@ic.ac.uk
License: GNU 3.0
Classifier: Programming Language :: Python
Classifier: Programming Language :: Python :: 3
Classifier: Programming Language :: Python :: 3.10
License-File: LICENSE
Requires-Dist: pandas
Requires-Dist: scikit-learn
Requires-Dist: numpy
Requires-Dist: setuptools
Requires-Dist: scipy
Requires-Dist: statsmodels
Requires-Dist: sspa
Requires-Dist: requests
Requires-Dist: gseapy
